[
  {
    "id": 1,
    "first_name": "Marge",
    "email": "mnorbury0@time.com",
    "gender": "Female"
  },
  {
    "id": 2,
    "first_name": "Clevie",
    "email": "cnavarijo1@ovh.net",
    "gender": "Male"
  },
  {
    "id": 3,
    "first_name": "Seumas",
    "email": "sserotsky2@nydailynews.com",
    "gender": "Male"
  },
  {
    "id": 4,
    "first_name": "Dyan",
    "email": "dplacidi3@sun.com",
    "gender": "Female"
  },
  {
    "id": 5,
    "first_name": "Grannie",
    "email": "gletteresse4@sciencedirect.com",
    "gender": "Male"
  },
  {
    "id": 6,
    "first_name": "Terese",
    "email": "tlegen5@i2i.jp",
    "gender": "Female"
  },
  {
    "id": 7,
    "first_name": "Ludwig",
    "email": "lfoulcher6@tripod.com",
    "gender": "Male"
  },
  {
    "id": 8,
    "first_name": "Luther",
    "email": "lcow7@acquirethisname.com",
    "gender": "Male"
  },
  {
    "id": 9,
    "first_name": "Mitchael",
    "email": "mmenichini8@topsy.com",
    "gender": "Male"
  },
  {
    "id": 10,
    "first_name": "Cherlyn",
    "email": "cdibben9@elpais.com",
    "gender": "Female"
  },
  {
    "id": 11,
    "first_name": "Ignacio",
    "email": "iwesterna@huffingtonpost.com",
    "gender": "Male"
  },
  {
    "id": 12,
    "first_name": "Stephen",
    "email": "sgutmanb@hexun.com",
    "gender": "Male"
  },
  {
    "id": 13,
    "first_name": "Yves",
    "email": "ygrinnikovc@nytimes.com",
    "gender": "Male"
  },
  {
    "id": 14,
    "first_name": "Grady",
    "email": "gmilesd@shareasale.com",
    "gender": "Male"
  },
  {
    "id": 15,
    "first_name": "Fanchon",
    "email": "fmuldoone@istockphoto.com",
    "gender": "Female"
  },
  {
    "id": 16,
    "first_name": "Shermie",
    "email": "sshrimplinf@xing.com",
    "gender": "Male"
  },
  {
    "id": 17,
    "first_name": "Aile",
    "email": "atidmasg@ca.gov",
    "gender": "Female"
  },
  {
    "id": 18,
    "first_name": "Melessa",
    "email": "mdahlenh@yellowbook.com",
    "gender": "Female"
  },
  {
    "id": 19,
    "first_name": "Frank",
    "email": "fgrebbini@discuz.net",
    "gender": "Male"
  },
  {
    "id": 20,
    "first_name": "Tallie",
    "email": "tjarvillej@flickr.com",
    "gender": "Male"
  }
]
